{
    "adid": null, 
    "name": "GARAGE DU LOIR", 
    "name_of_contact": null, 
    "scrape_page": "https://www.meilleur-garagiste.com/annuaire/garage-du-loir.441933.html", 
    "business_website": null, 
    "areas_covered": null, 
    "description": "Implantée à SEICHES SUR LOIR (49140) dans le département Maine-Et-Loire , l'entreprise GARAGE DU LOIR est spécialisée dans l'activité de Entretien véhicule (Entretien automobile) à SEICHES SUR LOIR . L'entreprise GARAGE DU LOIR est présente sur Meilleur-Garagiste.com depuis le 16/10/15. Les informations de GARAGE DU LOIR ont été mises à jour par Anthony Furois en qualité de GERANT le 02/05/16 à SEICHES SUR LOIR. GARAGE DU LOIR est une S.A.R.L. immatriculée sous le numéro siret 75191187600017 . Contactez GARAGE DU LOIR pour toute demande de devis Entretien véhicule !", 
    "img_link": null, 
    "hqdb_featured_ad_type": null, 
    "hqdb_nr_reviews": null, 
    "hqdb_review_score": null, 
    "accreditations": null, 
    "category": null, 
    "subcategory": null, 
    "street": "rue des tanneries", 
    "city": "SEICHES SUR LOIR", 
    "zipcode": "49140", 
    "formatted_address": "rue des tanneries, SEICHES SUR LOIR, 49140", 
    "country": "fr", 
    "office_number": "0241762222", 
    "office_number2": null, 
    "mobile_number": null, 
    "mobile_number2": null, 
    "unidentified_phone_numbers": null, 
    "latitude": "47.5758492", 
    "longitude": "-0.3600289", 
    "business_email": null, 
    "yelp_page": null, 
    "facebook": null, 
    "twitter": null, 
    "instagram": null, 
    "venue_images": "https://www.meilleur-garagiste.com/images/logo/logo-441933.jpg", 
    "opening_hours_raw": null, 
    "pricelist_link": [
        "https://www.meilleur-garagiste.com/annuaire/garage-du-loir.441933.html"
    ], 
    "services": [
        {
            "service_category": null, 
            "service": "Allumage", 
            "duration": null, 
            "price": null, 
            "description": null
        }, 
        {
            "service_category": null, 
            "service": "Amortisseurs", 
            "duration": null, 
            "price": null, 
            "description": null
        }, 
        {
            "service_category": null, 
            "service": "Attelage", 
            "duration": null, 
            "price": null, 
            "description": null
        }, 
        {
            "service_category": null, 
            "service": "Batterie Alternateur Démarreur", 
            "duration": null, 
            "price": null, 
            "description": null
        }, 
        {
            "service_category": null, 
            "service": "Batterie Start and Stop", 
            "duration": null, 
            "price": null, 
            "description": null
        }, 
        {
            "service_category": null, 
            "service": "Boite automatique", 
            "duration": null, 
            "price": null, 
            "description": null
        }, 
        {
            "service_category": null, 
            "service": "Climatisation", 
            "duration": null, 
            "price": null, 
            "description": null
        }, 
        {
            "service_category": null, 
            "service": "Courroie de distribution", 
            "duration": null, 
            "price": null, 
            "description": null
        }, 
        {
            "service_category": null, 
            "service": "Diagnostic électronique", 
            "duration": null, 
            "price": null, 
            "description": null
        }, 
        {
            "service_category": null, 
            "service": "Direction assistée", 
            "duration": null, 
            "price": null, 
            "description": null
        }, 
        {
            "service_category": null, 
            "service": "Dispositif de sécurité AirBag", 
            "duration": null, 
            "price": null, 
            "description": null
        }, 
        {
            "service_category": null, 
            "service": "Echappement catalyseur", 
            "duration": null, 
            "price": null, 
            "description": null
        }, 
        {
            "service_category": null, 
            "service": "Eclairage et visibilité", 
            "duration": null, 
            "price": null, 
            "description": null
        }, 
        {
            "service_category": null, 
            "service": "Electronique embarquée", 
            "duration": null, 
            "price": null, 
            "description": null
        }, 
        {
            "service_category": null, 
            "service": "Embrayage", 
            "duration": null, 
            "price": null, 
            "description": null
        }, 
        {
            "service_category": null, 
            "service": "Freinage", 
            "duration": null, 
            "price": null, 
            "description": null
        }, 
        {
            "service_category": null, 
            "service": "Injection diesel", 
            "duration": null, 
            "price": null, 
            "description": null
        }, 
        {
            "service_category": null, 
            "service": "Injection essence", 
            "duration": null, 
            "price": null, 
            "description": null
        }, 
        {
            "service_category": null, 
            "service": "Liaison au sol", 
            "duration": null, 
            "price": null, 
            "description": null
        }, 
        {
            "service_category": null, 
            "service": "Ordinateur de bord", 
            "duration": null, 
            "price": null, 
            "description": null
        }, 
        {
            "service_category": null, 
            "service": "Pare-brise", 
            "duration": null, 
            "price": null, 
            "description": null
        }, 
        {
            "service_category": null, 
            "service": "Plaque d'immatriculation", 
            "duration": null, 
            "price": null, 
            "description": null
        }, 
        {
            "service_category": null, 
            "service": "Pneumatique", 
            "duration": null, 
            "price": null, 
            "description": null
        }, 
        {
            "service_category": null, 
            "service": "Pré-contrôle technique", 
            "duration": null, 
            "price": null, 
            "description": null
        }, 
        {
            "service_category": null, 
            "service": "Refroidissement Moteur", 
            "duration": null, 
            "price": null, 
            "description": null
        }, 
        {
            "service_category": null, 
            "service": "Réglage anti-pollution", 
            "duration": null, 
            "price": null, 
            "description": null
        }, 
        {
            "service_category": null, 
            "service": "Réglage train avant", 
            "duration": null, 
            "price": null, 
            "description": null
        }, 
        {
            "service_category": null, 
            "service": "Réparation moteur / changement turbo", 
            "duration": null, 
            "price": null, 
            "description": null
        }, 
        {
            "service_category": null, 
            "service": "Révision constructeur", 
            "duration": null, 
            "price": null, 
            "description": null
        }, 
        {
            "service_category": null, 
            "service": "Roulement de roues", 
            "duration": null, 
            "price": null, 
            "description": null
        }, 
        {
            "service_category": null, 
            "service": "Transmission", 
            "duration": null, 
            "price": null, 
            "description": null
        }, 
        {
            "service_category": null, 
            "service": "Vidange", 
            "duration": null, 
            "price": null, 
            "description": null
        }
    ]
}