{
    "adid": null, 
    "name": "Axiom Accountants Ltd", 
    "name_of_contact": null, 
    "scrape_page": "http://www.accaglobal.com/uk/en/member/find-an-accountant/find-firm/results/details.html?isocountry=VN&location=&country=UK&firmname=a&organisationid=ACCA&hid=&pagenumber=37&resultsperpage=25&requestcount=10&advisorid=0891315", 
    "business_website": "http://www.axiomaccountants.com", 
    "areas_covered": null, 
    "description": null, 
    "img_link": null, 
    "hqdb_featured_ad_type": null, 
    "hqdb_nr_reviews": null, 
    "hqdb_review_score": null, 
    "accreditations": "Registered as auditors in the UK/Ireland by ACCA", 
    "category": null, 
    "subcategory": null, 
    "street": "42-44 Adelaide Street", 
    "city": "BRADFORD", 
    "zipcode": "BD50EA", 
    "formatted_address": "42-44 Adelaide Street, BRADFORD, BD50EA", 
    "country": "gb", 
    "office_number": null, 
    "office_number2": null, 
    "mobile_number": "07876638252", 
    "mobile_number2": null, 
    "unidentified_phone_numbers": null, 
    "latitude": "53.7879553", 
    "longitude": "-1.7521343", 
    "business_email": "jamal@axiomaccountants.com", 
    "yelp_page": null, 
    "facebook": null, 
    "twitter": null, 
    "instagram": null, 
    "venue_images": null, 
    "opening_hours_raw": null, 
    "pricelist_link": null, 
    "services": [
        {}
    ]
}