{
    "adid": null, 
    "name": "Anderson Anderson & Brown LLP", 
    "name_of_contact": null, 
    "scrape_page": "http://www.accaglobal.com/uk/en/member/find-an-accountant/find-firm/results/details.html?isocountry=VN&location=&country=UK&firmname=a&organisationid=ACCA&hid=&pagenumber=25&resultsperpage=25&requestcount=7&advisorid=3723221", 
    "business_website": "http://www.aab.uk", 
    "areas_covered": null, 
    "description": null, 
    "img_link": null, 
    "hqdb_featured_ad_type": null, 
    "hqdb_nr_reviews": null, 
    "hqdb_review_score": null, 
    "accreditations": null, 
    "category": null, 
    "subcategory": null, 
    "street": "Prime Four Business Park", 
    "city": "ABERDEEN", 
    "zipcode": "AB158PU", 
    "formatted_address": "Prime Four Business Park, ABERDEEN, AB158PU", 
    "country": "gb", 
    "office_number": "01224626007", 
    "office_number2": null, 
    "mobile_number": null, 
    "mobile_number2": null, 
    "unidentified_phone_numbers": null, 
    "latitude": "57.1505485", 
    "longitude": "-2.2272816", 
    "business_email": "accountants@aab.uk", 
    "yelp_page": null, 
    "facebook": null, 
    "twitter": null, 
    "instagram": null, 
    "venue_images": null, 
    "opening_hours_raw": null, 
    "pricelist_link": null, 
    "services": [
        {}
    ]
}