{
    "adid": null, 
    "name": "AG Corporates Limited", 
    "name_of_contact": null, 
    "scrape_page": "http://www.accaglobal.com/uk/en/member/find-an-accountant/find-firm/results/details.html?isocountry=VN&location=&country=UK&firmname=a&organisationid=ACCA&hid=&pagenumber=5&resultsperpage=25&requestcount=2&advisorid=1976018", 
    "business_website": "http://www.agcorporates.co.uk", 
    "areas_covered": null, 
    "description": null, 
    "img_link": null, 
    "hqdb_featured_ad_type": null, 
    "hqdb_nr_reviews": null, 
    "hqdb_review_score": null, 
    "accreditations": "Registered as auditors in the UK/Ireland by ACCA", 
    "category": null, 
    "subcategory": null, 
    "street": "41 Lytton Road", 
    "city": "LONDON", 
    "zipcode": "E111JQ", 
    "formatted_address": "41 Lytton Road, LONDON, E111JQ", 
    "country": "gb", 
    "office_number": "02085889759", 
    "office_number2": null, 
    "mobile_number": null, 
    "mobile_number2": null, 
    "unidentified_phone_numbers": null, 
    "latitude": "51.5722647", 
    "longitude": "0.0066334", 
    "business_email": "gilbert@agcorporates.co.uk", 
    "yelp_page": null, 
    "facebook": null, 
    "twitter": null, 
    "instagram": null, 
    "venue_images": null, 
    "opening_hours_raw": null, 
    "pricelist_link": null, 
    "services": [
        {}
    ]
}