{
    "adid": null, 
    "name": "ABN Consultancy (Norfolk) Ltd", 
    "name_of_contact": null, 
    "scrape_page": "http://www.accaglobal.com/uk/en/member/find-an-accountant/find-firm/results/details.html?isocountry=VN&location=&country=UK&firmname=a&organisationid=ACCA&hid=&pagenumber=5&resultsperpage=25&requestcount=2&advisorid=3876478", 
    "business_website": "http://www.abnconsultancy.com", 
    "areas_covered": null, 
    "description": null, 
    "img_link": null, 
    "hqdb_featured_ad_type": null, 
    "hqdb_nr_reviews": null, 
    "hqdb_review_score": null, 
    "accreditations": "Wholly composed of Chartered Certified Accountants", 
    "category": null, 
    "subcategory": null, 
    "street": "Beeston Regis", 
    "city": "SHERINGHAM", 
    "zipcode": "NR268SH", 
    "formatted_address": "Beeston Regis, SHERINGHAM, NR268SH", 
    "country": "gb", 
    "office_number": null, 
    "office_number2": null, 
    "mobile_number": "07957391205", 
    "mobile_number2": null, 
    "unidentified_phone_numbers": null, 
    "latitude": "52.9360668", 
    "longitude": "1.2265347", 
    "business_email": "stefan@abnconsultancy.com", 
    "yelp_page": null, 
    "facebook": null, 
    "twitter": null, 
    "instagram": null, 
    "venue_images": null, 
    "opening_hours_raw": null, 
    "pricelist_link": null, 
    "services": [
        {}
    ]
}