{
    "adid": null, 
    "name": "AJ Accountants (Southwest) Ltd.", 
    "name_of_contact": null, 
    "scrape_page": "http://www.accaglobal.com/uk/en/member/find-an-accountant/find-firm/results/details.html?isocountry=VN&location=&country=UK&firmname=a&organisationid=ACCA&hid=&pagenumber=5&resultsperpage=25&requestcount=2&advisorid=3582080", 
    "business_website": null, 
    "areas_covered": null, 
    "description": null, 
    "img_link": null, 
    "hqdb_featured_ad_type": null, 
    "hqdb_nr_reviews": null, 
    "hqdb_review_score": null, 
    "accreditations": null, 
    "category": null, 
    "subcategory": null, 
    "street": "Firsdown", 
    "city": "SALISBURY", 
    "zipcode": "SP51SW", 
    "formatted_address": "Firsdown, SALISBURY, SP51SW", 
    "country": "gb", 
    "office_number": null, 
    "office_number2": null, 
    "mobile_number": "07798714775", 
    "mobile_number2": null, 
    "unidentified_phone_numbers": null, 
    "latitude": "51.099624", 
    "longitude": "-1.7020684", 
    "business_email": "zlcox@live.co.uk", 
    "yelp_page": null, 
    "facebook": null, 
    "twitter": null, 
    "instagram": null, 
    "venue_images": null, 
    "opening_hours_raw": null, 
    "pricelist_link": null, 
    "services": [
        {}
    ]
}