{
    "adid": null, 
    "name": "Accendo Consulting Ltd", 
    "name_of_contact": null, 
    "scrape_page": "http://www.accaglobal.com/uk/en/member/find-an-accountant/find-firm/results/details.html?isocountry=VN&location=&country=UK&firmname=a&organisationid=ACCA&hid=&pagenumber=13&resultsperpage=25&requestcount=4&advisorid=1773291", 
    "business_website": "http://www.accendoca.co.uk", 
    "areas_covered": null, 
    "description": null, 
    "img_link": null, 
    "hqdb_featured_ad_type": null, 
    "hqdb_nr_reviews": null, 
    "hqdb_review_score": null, 
    "accreditations": "Registered as auditors in the UK/Ireland by ACCA", 
    "category": null, 
    "subcategory": null, 
    "street": "67 Field Avenue", 
    "city": "CANTERBURY", 
    "zipcode": "CT11TR", 
    "formatted_address": "67 Field Avenue, CANTERBURY, CT11TR", 
    "country": "gb", 
    "office_number": "02075235356", 
    "office_number2": null, 
    "mobile_number": null, 
    "mobile_number2": null, 
    "unidentified_phone_numbers": null, 
    "latitude": "51.2911968", 
    "longitude": "1.1076423", 
    "business_email": "asif@accendoca.co.uk", 
    "yelp_page": null, 
    "facebook": null, 
    "twitter": null, 
    "instagram": null, 
    "venue_images": null, 
    "opening_hours_raw": null, 
    "pricelist_link": null, 
    "services": [
        {}
    ]
}